{"title": "表单元素美化", "topic": null, "time": "2025-04-24 19:32:59", "label": [], "needPassword": false, "text": "`fieldset`和`legend`标签\n\n使用\n\n```html\n<fieldset>\n  <legend>Hi!</legend>\n  <h1>Hello</h1>\n</fieldset>\n```\n\n效果\n\n![image-20221004194348068](https://s2.loli.net/2022/10/04/HyYo8RSw2NpfQEz.png)\n\n\n\n`textarea`标签\n\n默认是`inline-block`可以设置为`block`来进行设置；或者定位为\n\n```\ntextarea{\nvertical-align:top;\n}\n```\n\n文本设置不换行省略号表示\n\n```\n.div{\nwidth:150px;\nover-flow:hidden;\nwhite-space:nowrap;\ntext-overflow:ellipsis;\n}\n```\n\n"}